Workbook
Name aporte: 'Página1'!$D$16
Name rendimento_carteira: 'Página1'!$D$12
Name patrimonio: 'Página1'!$D$19
Name sugestao_investimento: 'Página1'!$B$13
Name salario: 'Página1'!$D$11
Name qtd_anos: 'Página1'!$D$17
Name taxa_mensal: 'Página1'!$D$18

Sheet Página1
B10: CONFIGURAÇÕES
B11: Salário | D11: 5000
B12: Rendimento Carteira | D12: 0.01
B13: Sugestão de Investimento | D13: =D11*30% -> 1500
B15: INVESTIMENTO MENSAL
B16: Quanto Investir por mês? | D16: 500
B17: Por quantos anos? | D17: 5
B18: Taxa de Rendimento mensal? | D18: 0.01079
B19: Patrimônio acumulado? | D19: =FV(taxa_mensal,qtd_anos*12,-aporte) -> 41888.457
B20: Divendendos mensais? | D20: =patrimonio*rendimento_carteira -> 418.88457
B22: INVESTIMENTO MENSAL | D22: Dividendo
A23: 2 | B23: Quanto em 2 anos? | C23: =FV($D$18,$A23*12,-$D$16) -> 13613.814 | D23: =C23*rendimento_carteira -> 136.13814
A24: 5 | B24: Quanto em 5 anos? | C24: =FV($D$18,$A24*12,-$D$16) -> 41888.457 | D24: =C24*rendimento_carteira -> 418.88457
A25: 10 | B25: Quanto em 10 anos? | C25: =FV($D$18,$A25*12,-$D$16) -> 121642.11 | D25: =C25*rendimento_carteira -> 1216.4211
A26: 20 | B26: Quanto em 20 anos? | C26: =FV($D$18,$A26*12,-$D$16) -> 562599.2 | D26: =C26*rendimento_carteira -> 5625.992
A27: 30 | B27: Quanto em 30 anos? | C27: =FV($D$18,$A27*12,-$D$16) -> 2161084.8 | D27: =C27*rendimento_carteira -> 21610.848
B30: Perfil | C30: Moderado
B31: Valor a ser investido por mês | C31: =aporte -> 500
B33: Tipo de FII | C33: Percentual Sugerido | D33: Valores
B34: PAPEL | C34: =VLOOKUP($C$30&"-"&B34,'Página2'!A:D,4,FALSE) -> 0.32 | D34: =$C$31*C34 -> 160
B35: TIJOLO | C35: =VLOOKUP($C$30&"-"&B35,'Página2'!A:D,4,FALSE) -> 0.4 | D35: =$C$31*C35 -> 200
B36: HÍBRIDOS | C36: =VLOOKUP($C$30&"-"&B36,'Página2'!A:D,4,FALSE) -> 0.08 | D36: =$C$31*C36 -> 40
B37: FOFs | C37: =VLOOKUP($C$30&"-"&B37,'Página2'!A:D,4,FALSE) -> 0.1 | D37: =$C$31*C37 -> 50
B38: DESENVOLVIMENTO | C38: =VLOOKUP($C$30&"-"&B38,'Página2'!A:D,4,FALSE) -> 0.1 | D38: =$C$31*C38 -> 50
B39: HOTELARIAS | C39: =VLOOKUP($C$30&"-"&B39,'Página2'!A:D,4,FALSE) -> 0 | D39: =$C$31*C39 -> 0
D40: =SUM(D34:D39) -> 500

Sheet Página2
A3: CHAVE | B3: PERFIL | C3: TIPO DE FII | D3: %
A4: =B4&"-"&C4 -> Conservador-PAPEL | B4: Conservador | C4: PAPEL | D4: 0.3
A5: =B5&"-"&C5 -> Conservador-TIJOLO | B5: Conservador | C5: TIJOLO | D5: 0.5
A6: =B6&"-"&C6 -> Conservador-HÍBRIDOS | B6: Conservador | C6: HÍBRIDOS | D6: 0.1
A7: =B7&"-"&C7 -> Conservador-FOFs | B7: Conservador | C7: FOFs | D7: 0.1
A8: =B8&"-"&C8 -> Conservador-DESENVOLVIMENTO | B8: Conservador | C8: DESENVOLVIMENTO | D8: 0
A9: =B9&"-"&C9 -> Conservador-HOTELARIAS | B9: Conservador | C9: HOTELARIAS | D9: 0
A10: =B10&"-"&C10 -> Moderado-PAPEL | B10: Moderado | C10: PAPEL | D10: 0.32
A11: =B11&"-"&C11 -> Moderado-TIJOLO | B11: Moderado | C11: TIJOLO | D11: 0.4
A12: =B12&"-"&C12 -> Moderado-HÍBRIDOS | B12: Moderado | C12: HÍBRIDOS | D12: 0.08
A13: =B13&"-"&C13 -> Moderado-FOFs | B13: Moderado | C13: FOFs | D13: 0.1
A14: =B14&"-"&C14 -> Moderado-DESENVOLVIMENTO | B14: Moderado | C14: DESENVOLVIMENTO | D14: 0.1
A15: =B15&"-"&C15 -> Moderado-HOTELARIAS | B15: Moderado | C15: HOTELARIAS | D15: 0
... A21: =B21&"-"&C21 -> Agressivo-HOTELARIAS | B21: Agressivo | C21: HOTELARIAS | D21: 0.1
